{
  "total": 1301,
  "sefaria_200": 1301,
  "sefaria_404": 0,
  "sefaria_error": 0,
  "subclass_person": 319,
  "has_generation": 160,
  "has_any_edges": 140,
  "has_family_edges": 102,
  "has_opposed_edges": 37,
  "has_corresponded_edges": 10,
  "buckets": {
    "full": 126,
    "person_with_gen_no_edges": 34,
    "person_no_gen": 159,
    "not_person": 982,
    "not_in_sefaria": 0
  },
  "by_local_bio_source": {
    "sefaria": 962,
    "wikipedia": 339,
    "other": 0
  },
  "cross_tab_wikipedia_bio_x_sefaria_edges": {
    "wiki_bio_with_sefaria_edges": 8,
    "wiki_bio_no_sefaria_edges": 331,
    "sefaria_bio_with_sefaria_edges": 132,
    "sefaria_bio_no_sefaria_edges": 830
  },
  "numSources_distribution": {
    "n": 993,
    "min": 0,
    "p25": 52,
    "p50": 122,
    "p75": 289,
    "p90": 725,
    "p99": 10477,
    "max": 24353
  },
  "link_type_universe": {
    "is-a": 970,
    "displays-under": 898,
    "sheets-related-to": 663,
    "has-sheets-related-to": 632,
    "related-to": 505,
    "similar-to": 172,
    "participates-in": 144,
    "learned-from": 126,
    "has-gender": 105,
    "taught": 84,
    "has-participant": 77,
    "child-of": 74,
    "is-category-of": 67,
    "parent-of": 61,
    "possibility-for": 56,
    "dissimilar-to": 54,
    "member-of": 52,
    "person-participates-in-event": 47,
    "has-role": 43,
    "spouse-of": 40,
    "has-specific-dependence": 40,
    "opposed": 37,
    "has-relationship": 34,
    "temporally-contained-in": 28,
    "physically-contains": 22,
    "sibling-of": 21,
    "temporally-contains": 19,
    "event-has-person-participant": 19,
    "physically-contained-in": 19,
    "preceded-by": 13,
    "specifically-dependent-on": 13,
    "has-member": 12,
    "ancestor-of": 12,
    "precedes": 12,
    "corresponded-with": 10,
    "role-of": 10,
    "descendant-of": 9,
    "displays-above": 7,
    "child-in-law-of": 6,
    "adjacent-to": 6,
    "leader-of": 6,
    "synonymous-with": 6,
    "has-leader": 5,
    "parent-in-law-of": 5,
    "cousin-of": 2,
    "grandparent-of": 1,
    "relationship-of": 1,
    "grandchild-of": 1
  }
}